[
  {
    "actualDestinationAuthority": "Mission Planner",
    "actualSourceAuthority": "Event Detection",
    "artifactType": "EOEA-ART-002",
    "authorityDefectOpen": false,
    "bridgeId": "BRIDGE-EVENT-MISSION-001",
    "canonicalExecutionResult": "EXECUTED_ACCEPTED_BY_DESTINATION",
    "delegationChain": "EXPLICIT_OR_NOT_REQUIRED",
    "destination": "Mission Planner",
    "destinationAuthorityResult": "VALID",
    "exactRootCause": "PARTIAL_CANONICAL_IMPLEMENTATION_NOT_AUTHORITY",
    "externalDependencyStatus": "INTERNAL",
    "implementationStatus": "PARTIAL",
    "lifecycleState": "EWO-WF-000002",
    "priorRejectionCode": "EO-EB authority/provenance certification remains required for partial bridge implementation.",
    "promotionAuthority": "TC-002/EO-EB AuthorityPromotionAuthority",
    "proofDomain": "PAPER",
    "provenanceStatus": "VERIFIED",
    "remediationAction": "Assign to EO-EH/non-authority bridge implementation closure",
    "requiredDestinationAuthority": "Mission Planner",
    "requiredSourceAuthority": "Event Detection",
    "source": "Event Detection",
    "sourceAuthorityResult": "VALID",
    "workflowType": "operational initiation"
  },
  {
    "actualDestinationAuthority": "Analyst",
    "actualSourceAuthority": "Seeker",
    "artifactType": "EOEA-ART-006",
    "authorityDefectOpen": false,
    "bridgeId": "BRIDGE-SEEKER-ANALYST-001",
    "canonicalExecutionResult": "EXECUTED_ACCEPTED_BY_DESTINATION",
    "delegationChain": "EXPLICIT_OR_NOT_REQUIRED",
    "destination": "Analyst",
    "destinationAuthorityResult": "VALID",
    "exactRootCause": "PARTIAL_CANONICAL_IMPLEMENTATION_NOT_AUTHORITY",
    "externalDependencyStatus": "INTERNAL",
    "implementationStatus": "PARTIAL",
    "lifecycleState": "EWO-WF-000006",
    "priorRejectionCode": "EO-EB authority/provenance certification remains required for partial bridge implementation.",
    "promotionAuthority": "TC-002/EO-EB AuthorityPromotionAuthority",
    "proofDomain": "PAPER",
    "provenanceStatus": "VERIFIED",
    "remediationAction": "Assign to EO-EH/non-authority bridge implementation closure",
    "requiredDestinationAuthority": "Analyst",
    "requiredSourceAuthority": "Seeker",
    "source": "Seeker",
    "sourceAuthorityResult": "VALID",
    "workflowType": "strategic discovery"
  },
  {
    "actualDestinationAuthority": "Risk",
    "actualSourceAuthority": "Analyst",
    "artifactType": "EOEA-ART-007",
    "authorityDefectOpen": false,
    "bridgeId": "BRIDGE-ANALYST-RISK-001",
    "canonicalExecutionResult": "EXECUTED_ACCEPTED_BY_DESTINATION",
    "delegationChain": "EXPLICIT_OR_NOT_REQUIRED",
    "destination": "Risk",
    "destinationAuthorityResult": "VALID",
    "exactRootCause": "PARTIAL_CANONICAL_IMPLEMENTATION_NOT_AUTHORITY",
    "externalDependencyStatus": "INTERNAL",
    "implementationStatus": "PARTIAL",
    "lifecycleState": "EWO-WF-000007",
    "priorRejectionCode": "EO-EB authority/provenance certification remains required for partial bridge implementation.",
    "promotionAuthority": "TC-002/EO-EB AuthorityPromotionAuthority",
    "proofDomain": "PAPER",
    "provenanceStatus": "VERIFIED",
    "remediationAction": "Assign to EO-EH/non-authority bridge implementation closure",
    "requiredDestinationAuthority": "Risk",
    "requiredSourceAuthority": "Analyst",
    "source": "Analyst",
    "sourceAuthorityResult": "VALID",
    "workflowType": "strategic discovery"
  },
  {
    "actualDestinationAuthority": "Authorization Authority",
    "actualSourceAuthority": "Risk",
    "artifactType": "EOEA-ART-008",
    "authorityDefectOpen": false,
    "bridgeId": "BRIDGE-RISK-AUTH-001",
    "canonicalExecutionResult": "EXECUTED_ACCEPTED_BY_DESTINATION",
    "delegationChain": "EXPLICIT_OR_NOT_REQUIRED",
    "destination": "Authorization Authority",
    "destinationAuthorityResult": "VALID",
    "exactRootCause": "PARTIAL_CANONICAL_IMPLEMENTATION_NOT_AUTHORITY",
    "externalDependencyStatus": "INTERNAL",
    "implementationStatus": "PARTIAL",
    "lifecycleState": "EWO-WF-000008",
    "priorRejectionCode": "EO-EB authority/provenance certification remains required for partial bridge implementation.",
    "promotionAuthority": "TC-002/EO-EB AuthorityPromotionAuthority",
    "proofDomain": "PAPER",
    "provenanceStatus": "VERIFIED",
    "remediationAction": "Assign to EO-EH/non-authority bridge implementation closure",
    "requiredDestinationAuthority": "Authorization Authority",
    "requiredSourceAuthority": "Risk",
    "source": "Risk",
    "sourceAuthorityResult": "VALID",
    "workflowType": "decision and authorization"
  },
  {
    "actualDestinationAuthority": "Trader",
    "actualSourceAuthority": "Authorization Authority",
    "artifactType": "EOEA-ART-009",
    "authorityDefectOpen": false,
    "bridgeId": "BRIDGE-AUTH-TRADER-001",
    "canonicalExecutionResult": "EXECUTED_ACCEPTED_BY_DESTINATION",
    "delegationChain": "EXPLICIT_OR_NOT_REQUIRED",
    "destination": "Trader",
    "destinationAuthorityResult": "VALID",
    "exactRootCause": "PARTIAL_CANONICAL_IMPLEMENTATION_NOT_AUTHORITY",
    "externalDependencyStatus": "INTERNAL",
    "implementationStatus": "PARTIAL",
    "lifecycleState": "EWO-WF-000009",
    "priorRejectionCode": "EO-EB authority/provenance certification remains required for partial bridge implementation.",
    "promotionAuthority": "TC-002/EO-EB AuthorityPromotionAuthority",
    "proofDomain": "PAPER",
    "provenanceStatus": "VERIFIED",
    "remediationAction": "Assign to EO-EH/non-authority bridge implementation closure",
    "requiredDestinationAuthority": "Trader",
    "requiredSourceAuthority": "Authorization Authority",
    "source": "Authorization Authority",
    "sourceAuthorityResult": "VALID",
    "workflowType": "decision and authorization"
  },
  {
    "actualDestinationAuthority": "Fill Ledger",
    "actualSourceAuthority": "Paper Broker",
    "artifactType": "EOEA-ART-011",
    "authorityDefectOpen": false,
    "bridgeId": "BRIDGE-BROKER-FILL-001",
    "canonicalExecutionResult": "EXECUTED_ACCEPTED_BY_DESTINATION",
    "delegationChain": "EXPLICIT_OR_NOT_REQUIRED",
    "destination": "Fill Ledger",
    "destinationAuthorityResult": "VALID",
    "exactRootCause": "PARTIAL_CANONICAL_IMPLEMENTATION_NOT_AUTHORITY",
    "externalDependencyStatus": "EXTERNAL_BOUNDARY",
    "implementationStatus": "PARTIAL",
    "lifecycleState": "EWO-WF-000011",
    "priorRejectionCode": "EO-EB authority/provenance certification remains required for partial bridge implementation.",
    "promotionAuthority": "TC-002/EO-EB AuthorityPromotionAuthority",
    "proofDomain": "PAPER",
    "provenanceStatus": "VERIFIED",
    "remediationAction": "Assign to EO-EH/non-authority bridge implementation closure",
    "requiredDestinationAuthority": "Fill Ledger",
    "requiredSourceAuthority": "Paper Broker",
    "source": "Paper Broker",
    "sourceAuthorityResult": "VALID",
    "workflowType": "entry execution"
  },
  {
    "actualDestinationAuthority": "EO-CK",
    "actualSourceAuthority": "Position Registry",
    "artifactType": "EOEA-ART-014",
    "authorityDefectOpen": false,
    "bridgeId": "BRIDGE-POSITION-EOCK-001",
    "canonicalExecutionResult": "EXECUTED_ACCEPTED_BY_DESTINATION",
    "delegationChain": "EXPLICIT_OR_NOT_REQUIRED",
    "destination": "EO-CK",
    "destinationAuthorityResult": "VALID",
    "exactRootCause": "PARTIAL_CANONICAL_IMPLEMENTATION_NOT_AUTHORITY",
    "externalDependencyStatus": "INTERNAL",
    "implementationStatus": "PARTIAL",
    "lifecycleState": "EWO-WF-000014",
    "priorRejectionCode": "EO-EB authority/provenance certification remains required for partial bridge implementation.",
    "promotionAuthority": "TC-002/EO-EB AuthorityPromotionAuthority",
    "proofDomain": "PAPER",
    "provenanceStatus": "VERIFIED",
    "remediationAction": "Assign to EO-EH/non-authority bridge implementation closure",
    "requiredDestinationAuthority": "EO-CK",
    "requiredSourceAuthority": "Position Registry",
    "source": "Position Registry",
    "sourceAuthorityResult": "VALID",
    "workflowType": "position monitoring"
  },
  {
    "actualDestinationAuthority": "Surveillance",
    "actualSourceAuthority": "EO-CK",
    "artifactType": "EOEA-ART-015",
    "authorityDefectOpen": false,
    "bridgeId": "BRIDGE-EOCK-SURVEILLANCE-001",
    "canonicalExecutionResult": "EXECUTED_ACCEPTED_BY_DESTINATION",
    "delegationChain": "EXPLICIT_OR_NOT_REQUIRED",
    "destination": "Surveillance",
    "destinationAuthorityResult": "VALID",
    "exactRootCause": "PARTIAL_CANONICAL_IMPLEMENTATION_NOT_AUTHORITY",
    "externalDependencyStatus": "INTERNAL",
    "implementationStatus": "PARTIAL",
    "lifecycleState": "EWO-WF-000015",
    "priorRejectionCode": "EO-EB authority/provenance certification remains required for partial bridge implementation.",
    "promotionAuthority": "TC-002/EO-EB AuthorityPromotionAuthority",
    "proofDomain": "PAPER",
    "provenanceStatus": "VERIFIED",
    "remediationAction": "Assign to EO-EH/non-authority bridge implementation closure",
    "requiredDestinationAuthority": "Surveillance",
    "requiredSourceAuthority": "EO-CK",
    "source": "EO-CK",
    "sourceAuthorityResult": "VALID",
    "workflowType": "position monitoring"
  },
  {
    "actualDestinationAuthority": "Exit Decision",
    "actualSourceAuthority": "Surveillance",
    "artifactType": "EOEA-ART-016",
    "authorityDefectOpen": false,
    "bridgeId": "BRIDGE-SURVEILLANCE-EXIT-001",
    "canonicalExecutionResult": "EXECUTED_ACCEPTED_BY_DESTINATION",
    "delegationChain": "EXPLICIT_OR_NOT_REQUIRED",
    "destination": "Exit Decision",
    "destinationAuthorityResult": "VALID",
    "exactRootCause": "PARTIAL_CANONICAL_IMPLEMENTATION_NOT_AUTHORITY",
    "externalDependencyStatus": "INTERNAL",
    "implementationStatus": "PARTIAL",
    "lifecycleState": "EWO-WF-000016",
    "priorRejectionCode": "EO-EB authority/provenance certification remains required for partial bridge implementation.",
    "promotionAuthority": "TC-002/EO-EB AuthorityPromotionAuthority",
    "proofDomain": "PAPER",
    "provenanceStatus": "VERIFIED",
    "remediationAction": "Assign to EO-EH/non-authority bridge implementation closure",
    "requiredDestinationAuthority": "Exit Decision",
    "requiredSourceAuthority": "Surveillance",
    "source": "Surveillance",
    "sourceAuthorityResult": "VALID",
    "workflowType": "position monitoring"
  },
  {
    "actualDestinationAuthority": "Authorization Authority",
    "actualSourceAuthority": "Exit Decision",
    "artifactType": "EOEA-ART-017",
    "authorityDefectOpen": false,
    "bridgeId": "BRIDGE-EXIT-AUTH-001",
    "canonicalExecutionResult": "EXECUTED_ACCEPTED_BY_DESTINATION",
    "delegationChain": "EXPLICIT_OR_NOT_REQUIRED",
    "destination": "Authorization Authority",
    "destinationAuthorityResult": "VALID",
    "exactRootCause": "PARTIAL_CANONICAL_IMPLEMENTATION_NOT_AUTHORITY",
    "externalDependencyStatus": "INTERNAL",
    "implementationStatus": "PARTIAL",
    "lifecycleState": "EWO-WF-000017",
    "priorRejectionCode": "EO-EB authority/provenance certification remains required for partial bridge implementation.",
    "promotionAuthority": "TC-002/EO-EB AuthorityPromotionAuthority",
    "proofDomain": "PAPER",
    "provenanceStatus": "VERIFIED",
    "remediationAction": "Assign to EO-EH/non-authority bridge implementation closure",
    "requiredDestinationAuthority": "Authorization Authority",
    "requiredSourceAuthority": "Exit Decision",
    "source": "Exit Decision",
    "sourceAuthorityResult": "VALID",
    "workflowType": "exit execution"
  },
  {
    "actualDestinationAuthority": "Performance Truth",
    "actualSourceAuthority": "Closed Position Truth",
    "artifactType": "EOEA-ART-021",
    "authorityDefectOpen": false,
    "bridgeId": "BRIDGE-CPT-PT-001",
    "canonicalExecutionResult": "EXECUTED_ACCEPTED_BY_DESTINATION",
    "delegationChain": "EXPLICIT_OR_NOT_REQUIRED",
    "destination": "Performance Truth",
    "destinationAuthorityResult": "VALID",
    "exactRootCause": "PARTIAL_CANONICAL_IMPLEMENTATION_NOT_AUTHORITY",
    "externalDependencyStatus": "INTERNAL",
    "implementationStatus": "PARTIAL",
    "lifecycleState": "EWO-WF-000021",
    "priorRejectionCode": "EO-EB authority/provenance certification remains required for partial bridge implementation.",
    "promotionAuthority": "TC-002/EO-EB AuthorityPromotionAuthority",
    "proofDomain": "PAPER",
    "provenanceStatus": "VERIFIED",
    "remediationAction": "Assign to EO-EH/non-authority bridge implementation closure",
    "requiredDestinationAuthority": "Performance Truth",
    "requiredSourceAuthority": "Closed Position Truth",
    "source": "Closed Position Truth",
    "sourceAuthorityResult": "VALID",
    "workflowType": "performance truth"
  },
  {
    "actualDestinationAuthority": "Historian",
    "actualSourceAuthority": "Performance Truth",
    "artifactType": "EOEA-ART-022",
    "authorityDefectOpen": false,
    "bridgeId": "BRIDGE-PT-HISTORIAN-001",
    "canonicalExecutionResult": "EXECUTED_ACCEPTED_BY_DESTINATION",
    "delegationChain": "EXPLICIT_OR_NOT_REQUIRED",
    "destination": "Historian",
    "destinationAuthorityResult": "VALID",
    "exactRootCause": "PARTIAL_CANONICAL_IMPLEMENTATION_NOT_AUTHORITY",
    "externalDependencyStatus": "INTERNAL",
    "implementationStatus": "PARTIAL",
    "lifecycleState": "EWO-WF-000022",
    "priorRejectionCode": "EO-EB authority/provenance certification remains required for partial bridge implementation.",
    "promotionAuthority": "TC-002/EO-EB AuthorityPromotionAuthority",
    "proofDomain": "PAPER",
    "provenanceStatus": "VERIFIED",
    "remediationAction": "Assign to EO-EH/non-authority bridge implementation closure",
    "requiredDestinationAuthority": "Historian",
    "requiredSourceAuthority": "Performance Truth",
    "source": "Performance Truth",
    "sourceAuthorityResult": "VALID",
    "workflowType": "performance truth"
  },
  {
    "actualDestinationAuthority": "Learning Systems",
    "actualSourceAuthority": "Historian",
    "artifactType": "EOEA-ART-023",
    "authorityDefectOpen": false,
    "bridgeId": "BRIDGE-HISTORIAN-LEARNING-001",
    "canonicalExecutionResult": "EXECUTED_ACCEPTED_BY_DESTINATION",
    "delegationChain": "EXPLICIT_OR_NOT_REQUIRED",
    "destination": "Learning Systems",
    "destinationAuthorityResult": "VALID",
    "exactRootCause": "PARTIAL_CANONICAL_IMPLEMENTATION_NOT_AUTHORITY",
    "externalDependencyStatus": "INTERNAL",
    "implementationStatus": "PARTIAL",
    "lifecycleState": "EWO-WF-000023",
    "priorRejectionCode": "EO-EB authority/provenance certification remains required for partial bridge implementation.",
    "promotionAuthority": "TC-002/EO-EB AuthorityPromotionAuthority",
    "proofDomain": "PAPER",
    "provenanceStatus": "VERIFIED",
    "remediationAction": "Assign to EO-EH/non-authority bridge implementation closure",
    "requiredDestinationAuthority": "Learning Systems",
    "requiredSourceAuthority": "Historian",
    "source": "Historian",
    "sourceAuthorityResult": "VALID",
    "workflowType": "performance truth"
  },
  {
    "actualDestinationAuthority": "Analyst",
    "actualSourceAuthority": "Communications Bus",
    "artifactType": "EOEA-ART-026",
    "authorityDefectOpen": false,
    "bridgeId": "BRIDGE-FRESHNESS-ANALYTICAL-001",
    "canonicalExecutionResult": "EXECUTED_ACCEPTED_BY_DESTINATION",
    "delegationChain": "EXPLICIT_OR_NOT_REQUIRED",
    "destination": "Analyst",
    "destinationAuthorityResult": "VALID",
    "exactRootCause": "PARTIAL_CANONICAL_IMPLEMENTATION_NOT_AUTHORITY",
    "externalDependencyStatus": "INTERNAL",
    "implementationStatus": "PARTIAL",
    "lifecycleState": "EWO-WF-000026",
    "priorRejectionCode": "EO-EB authority/provenance certification remains required for partial bridge implementation.",
    "promotionAuthority": "TC-002/EO-EB AuthorityPromotionAuthority",
    "proofDomain": "PAPER",
    "provenanceStatus": "VERIFIED",
    "remediationAction": "Assign to EO-EH/non-authority bridge implementation closure",
    "requiredDestinationAuthority": "Analyst",
    "requiredSourceAuthority": "Communications Bus",
    "source": "Communications Bus",
    "sourceAuthorityResult": "VALID",
    "workflowType": "operational governance"
  }
]